scriptifier/__init__.py
scriptifier/puppet_script.py
scriptifier/scriptifier.py
scriptifier-0.0.14.dist-info/LICENSE
scriptifier-0.0.14.dist-info/METADATA
scriptifier-0.0.14.dist-info/WHEEL
scriptifier-0.0.14.dist-info/top_level.txt
scriptifier-0.0.14.dist-info/RECORD
