Metadata-Version: 2.1
Name: scriptifier
Version: 0.0.14
Summary: A Python package that allows to run a function in a separated script, seamlessly.
Home-page: https://github.com/ben981/scriptifier
Author: ben981
Author-email: beniamino.vigano@protonmail.com
License: MIT
Keywords: scriptify,processify,processifier,subprocess,multiprocessing,memory,leak
Platform: UNKNOWN
License-File: LICENSE
